README.md
setup.py
sdscmt/__init__.py
sdscmt/cert_conversion_tool.py
sdscmt/generate_cert.py
sdscmt/generate_self_signed_cert.py
sdscmt/read_certificate.py
sdscmt/read_private_key.py
sdscmt/sdscmt.py
sdscmt.egg-info/PKG-INFO
sdscmt.egg-info/SOURCES.txt
sdscmt.egg-info/dependency_links.txt
sdscmt.egg-info/entry_points.txt
sdscmt.egg-info/requires.txt
sdscmt.egg-info/top_level.txt
sdscmt/sdcfc/PKCS12viewer.py
sdscmt/sdcfc/__init__.py
sdscmt/sdcfc/sdcfc.py
sdscmt/sdcfc/testing_sdfc.py
sdscmt/sdcfc/converters/__init__.py
sdscmt/sdcfc/converters/der_to_pem.py
sdscmt/sdcfc/converters/der_to_pkcs12.py
sdscmt/sdcfc/converters/pem_to_der.py
sdscmt/sdcfc/converters/pem_to_pkcs12.py
sdscmt/sdcfc/converters/pkcs12_to_pem.py