Metadata-Version: 2.1
Name: sdscmt
Version: 0.1.4.1
Summary: SDSCMT(Secure Data SSL Certificate Management Tool) It is comprehensive tool for generating, renewing, storing and monitoring Self Signed SSL certificates, ensuring enhanced security and streamlined management.
Home-page: https://github.com/shubham10divakar/sdscmt
Author: Subham Divakar
Author-email: shubham.divakar@gmail.com
License: UNKNOWN
Platform: UNKNOWN
Classifier: Programming Language :: Python :: 3
Classifier: License :: OSI Approved :: MIT License
Classifier: Operating System :: OS Independent
